cepik_vehicle_history_client/__init__.py
cepik_vehicle_history_client/client.py
cepik_vehicle_history_client-0.1.1.dist-info/LICENSE
cepik_vehicle_history_client-0.1.1.dist-info/METADATA
cepik_vehicle_history_client-0.1.1.dist-info/WHEEL
cepik_vehicle_history_client-0.1.1.dist-info/RECORD
