Metadata-Version: 2.3
Name: cepik-vehicle-history-client
Version: 0.1.1
Summary: A Python client for the CEPiK vehicle history service.
Author: Mateusz Tatko
Author-email: mtatko@mtatko.dev
Requires-Python: >=3.13
Classifier: Programming Language :: Python :: 3
Classifier: Programming Language :: Python :: 3.13
Requires-Dist: requests (>=2.32.3,<3.0.0)
